odoo10_addon_stock_picking_delivery_info_computation-10.0.1.0.1-nspkg.pth
odoo/addons/stock_picking_delivery_info_computation/README.rst
odoo/addons/stock_picking_delivery_info_computation/__init__.py
odoo/addons/stock_picking_delivery_info_computation/__manifest__.py
odoo/addons/stock_picking_delivery_info_computation/i18n/stock_picking_delivery_info_computation.pot
odoo/addons/stock_picking_delivery_info_computation/models/__init__.py
odoo/addons/stock_picking_delivery_info_computation/models/sale_order.py
odoo/addons/stock_picking_delivery_info_computation/models/stock_picking.py
odoo/addons/stock_picking_delivery_info_computation/readme/CONTRIBUTORS.rst
odoo/addons/stock_picking_delivery_info_computation/readme/DESCRIPTION.rst
odoo/addons/stock_picking_delivery_info_computation/readme/USAGE.rst
odoo/addons/stock_picking_delivery_info_computation/report/report_deliveryslip.xml
odoo/addons/stock_picking_delivery_info_computation/report/report_shipping.xml
odoo/addons/stock_picking_delivery_info_computation/static/description/icon.png
odoo/addons/stock_picking_delivery_info_computation/static/description/index.html
odoo/addons/stock_picking_delivery_info_computation/tests/__init__.py
odoo/addons/stock_picking_delivery_info_computation/tests/test_stock_picking_info_computation.py
odoo/addons/stock_picking_delivery_info_computation/views/delivery_view.xml
odoo10_addon_stock_picking_delivery_info_computation-10.0.1.0.1.dist-info/METADATA
odoo10_addon_stock_picking_delivery_info_computation-10.0.1.0.1.dist-info/WHEEL
odoo10_addon_stock_picking_delivery_info_computation-10.0.1.0.1.dist-info/namespace_packages.txt
odoo10_addon_stock_picking_delivery_info_computation-10.0.1.0.1.dist-info/top_level.txt
odoo10_addon_stock_picking_delivery_info_computation-10.0.1.0.1.dist-info/RECORD
